mental_health_and_prevalence.py
mental_health_and_prevalence-0.0.3.dist-info/METADATA
mental_health_and_prevalence-0.0.3.dist-info/WHEEL
mental_health_and_prevalence-0.0.3.dist-info/entry_points.txt
mental_health_and_prevalence-0.0.3.dist-info/top_level.txt
mental_health_and_prevalence-0.0.3.dist-info/RECORD
