Metadata-Version: 2.1
Name: mental-health-and-prevalence
Version: 0.0.3
Summary: Trends in the incidence of psychosis worldwide
Home-page: https://github.com/RikoWatanabe/MentalHelse.git
Author: riko watanabe
Author-email: s2022039@stu.musashino-u.ac.jp
License: UNKNOWN
Project-URL: Bug Tracker, https://github.com/RikoWatanabe/MentalHelse.git
Platform: UNKNOWN
Classifier: Programming Language :: Python :: 3
Classifier: License :: OSI Approved :: MIT License
Classifier: Operating System :: OS Independent
Requires-Python: >=3.7
